[{"image": "https://i.redd.it/r4jwfnefy3rc1.png", "subreddit": "pcmasterrace", "title": "Honestly, name another one"}, {"image": "https://i.redd.it/pa861fq1l3rc1.png", "subreddit": "facepalm", "title": "Have no ideas why"}, {"image": "https://i.redd.it/7ma2zvujm4rc1.png", "subreddit": "shitposting", "title": "Learn"}, {"image": "https://i.redd.it/fe3q47gpo4rc1.png", "subreddit": "comics", "title": "Motivation"}, {"image": "https://i.redd.it/ice4kr49n4rc1.png", "subreddit": "Funnymemes", "title": "Innocent mind"}, {"image": "https://i.redd.it/5ogkj2g1b4rc1.png", "subreddit": "gaming", "title": "AC Unity, the game that is surprising me a lot on so many aspects, for a 10 years old game. "}, {"image": "https://i.redd.it/elnnnx9cz4rc1.png", "subreddit": "BikiniBottomTwitter", "title": "it's a shame that it's gone, only loopholes for billionaires now"}, {"image": "https://i.redd.it/ticfdf2862rc1.png", "subreddit": "AdviceAnimals", "title": "SATAN For President"}, {"image": "https://i.redd.it/fksh9fbco4rc1.png", "subreddit": "Tinder", "title": "Took a gamble. Might not pay off but worth a shot"}, {"image": "https://i.redd.it/m034rjalq3rc1.png", "subreddit": "starterpacks", "title": "Annoying early 1900s techbro starterpack"}, {"image": "https://i.redd.it/qw5sbopua4rc1.png", "subreddit": "dataisbeautiful", "title": "[OC] Annual Rainfall Average in inches by US County"}, {"image": "https://i.redd.it/lme6tb2ex2rc1.png", "subreddit": "HistoryPorn", "title": "Policemen arresting a demonstrator when local people blocked the march of the British Union of Fascists in Cable Street in London\u2019s East End. 4 October 1936. [1200 x 876]."}, {"image": "https://i.redd.it/sffuwgsy14rc1.png", "subreddit": "wallpaper", "title": "In The Streets of Scandinavia by Kevin Gnutzmans [3840x2160]"}, {"image": "https://i.redd.it/799r3ztpq2rc1.png", "subreddit": "wallpapers", "title": "Funny wallpaper: Inside The Church"}, {"image": "https://i.redd.it/ee87iyzeazqc1.png", "subreddit": "BoneAppleTea", "title": "Fun the Mental"}, {"image": "https://i.redd.it/cx2x58duw4rc1.png", "subreddit": "Minecraft", "title": "I. Hate. Lightning."}, {"image": "https://ogre.natalie.mu/media/news/comic/2024/0328/dungeonmeshi2nd0328_15.jpg", "subreddit": "anime", "title": "'Delicious in Dungeon (Dungeon Meshi)' 2nd Cour Key Visual"}, {"image": "https://i.redd.it/icia3k6ic3rc1.png", "subreddit": "Animemes", "title": "Top 10 training arcs of all time "}, {"image": "https://i.redd.it/t8kz6a6eh4rc1.png", "subreddit": "memes", "title": "Please wait. I swear it gets better!"}, {"image": "https://i.redd.it/zw1aytzxc4rc1.png", "subreddit": "AbandonedPorn", "title": "An Abandoned Farm Mansion In The Deep South! "}, {"image": "https://i.redd.it/61fvkksjd3rc1.png", "subreddit": "MadeMeSmile", "title": "A love that lasts a long time."}, {"image": "https://i.redd.it/ern6nj5l83rc1.png", "subreddit": "anime", "title": "r/anime's Favorite Music Anime Poll Results"}, {"image": "https://i.redd.it/uc9e6akg7sqc1.png", "subreddit": "therewasanattempt", "title": "To do your job... "}, {"image": "https://i.imgur.com/d9FXUpx.jpg", "subreddit": "Wellthatsucks", "title": "Customer said their bathroom fan wasn't working."}, {"image": "https://i.redd.it/kp735ujnc4rc1.png", "subreddit": "dankmemes", "title": "Diseconomics "}, {"image": "https://i.redd.it/6ypepbm1v2rc1.png", "subreddit": "tumblr", "title": "The Death of Third Places"}, {"image": "https://i.redd.it/r6nwq758d3rc1.png", "subreddit": "shitposting", "title": "."}, {"image": "https://i.redd.it/k0glgzv0x4rc1.png", "subreddit": "DotA2", "title": "Everyone just disconnected at once yet they are still playing but the game doesn't count?"}, {"image": "https://i.redd.it/2w1dllgbx1rc1.png", "subreddit": "Art", "title": "Fantasy Burlesque Portrait (based on Pin-Up EvaMonroex), by MetaMeta (me), Krita, 2024"}, {"image": "https://i.redd.it/3i7eo6dms2rc1.png", "subreddit": "memes", "title": "*refuses to elaborate*"}, {"image": "https://i.redd.it/q1btzdjt85rc1.png", "subreddit": "Minecraft", "title": "What do you think of 1.21 now that Mojang announced there won't be anymore major features added to the update?"}, {"image": "https://i.redd.it/8cg45f5ka4rc1.png", "subreddit": "DotA2", "title": "Oracle when he gets MVP"}, {"image": "https://i.redd.it/92alsitxx2rc1.png", "subreddit": "Tinder", "title": "Fellas it ended well (kind of a part 2) "}, {"image": "https://i.redd.it/8y5jsi0h92rc1.png", "subreddit": "Minecraft", "title": "Nether portal WORKS with crying obsidian for some reason"}, {"image": "https://i.redd.it/74oml4yf72rc1.png", "subreddit": "comics", "title": "Holy"}, {"image": "https://i.redd.it/23j79r07f5rc1.png", "subreddit": "wholesomememes", "title": "You'll always have a friend by your side"}, {"image": "https://i.redd.it/qrywa0c8v4rc1.png", "subreddit": "starterpacks", "title": "Sober metalhead starter pack"}, {"image": "https://i.redd.it/wq1uqyvms2rc1.png", "subreddit": "cursedcomments", "title": "cursed idea, ending up burned"}, {"image": "https://i.imgur.com/aegAbgA.png", "subreddit": "OldSchoolCool", "title": "Joey Ramone and his prom date, c. 1969"}, {"image": "https://i.imgur.com/EdOw7yy.png", "subreddit": "trippinthroughtime", "title": "Just another day..."}, {"image": "https://i.redd.it/njggh3eso3rc1.png", "subreddit": "wholesomememes", "title": "family is first that was appreciated"}, {"image": "https://i.redd.it/vugfh0er43rc1.png", "subreddit": "Minecraft", "title": "The new stuff is cool, but when are we going to get new paintings?"}, {"image": "https://i.redd.it/m6x9vmbap3rc1.png", "subreddit": "HolUp", "title": "Mysterious young grandmother."}, {"image": "https://i.redd.it/kybtsctva4rc1.png", "subreddit": "dataisbeautiful", "title": "Border encounters by state since the beginning of FY 2020 [OC]"}, {"image": "https://i.redd.it/nbq9b1rm45rc1.png", "subreddit": "ProgrammerHumor", "title": "didYouKnow"}, {"image": "https://i.redd.it/b1qcvmrqo3rc1.png", "subreddit": "Tinder", "title": "My Tinder insights as a straight 22M"}, {"image": "https://i.redd.it/7lq5e112j2rc1.png", "subreddit": "facepalm", "title": "Sex offenders vs sex defenders"}, {"image": "https://i.redd.it/gw12uugk34rc1.png", "subreddit": "starterpacks", "title": "The 1950's Prepper Starterpack"}, {"image": "https://i.redd.it/5p24tmrj83rc1.png", "subreddit": "pcmasterrace", "title": "Dog stepped on keyboard, created uncopyable symbol"}, {"image": "https://i.redd.it/jkciqsgs43rc1.png", "subreddit": "gardening", "title": "Bougainvillea... "}, {"image": "https://i.redd.it/72djrdq3o3rc1.png", "subreddit": "facepalm", "title": "That's why you should read the information carefully"}, {"image": "https://i.redd.it/cxzgyp9ck5rc1.png", "subreddit": "aww", "title": "i found these little kitties on the street a while a go and decided to take them home sooo cuteee!"}, {"image": "https://i.redd.it/gjzgvu0914rc1.png", "subreddit": "dankmemes", "title": "I amn't letting you tell me what's a word and what'sn't"}, {"image": "https://i.imgur.com/XE9Qetn.jpg", "subreddit": "gardening", "title": "Ready for warm weather"}, {"image": "https://i.redd.it/v5xdfwd0w2rc1.png", "subreddit": "Animemes", "title": "Both"}, {"image": "https://cdn.discordapp.com/attachments/1018687366333992993/1222936155125842012/Pasted_image_98.png?ex=6618070c&is=6605920c&hm=10ad57395d786ee9f6a2587eb776e28b2fb1aea5835e91cd3fd933f7449fbbd9&", "subreddit": "terriblefacebookmemes", "title": "Here's a meme from a guy who definitely doesn't adhere to the spinning space ball religion:"}, {"image": "https://i.redd.it/cam4sdkvb5rc1.png", "subreddit": "softwaregore", "title": "How am i supposed to rate it then? "}, {"image": "https://i.redd.it/s6k2cmtga3rc1.png", "subreddit": "wholesomememes", "title": "Anon is not less than an angel"}, {"image": "https://i.redd.it/hncwtkvg24rc1.png", "subreddit": "wallpaper", "title": "Times Square At 3:53 P.M., Winter, 1985 by Richard Estes [3840x2160]"}, {"image": "https://i.redd.it/45dsuf2ci3rc1.png", "subreddit": "facepalm", "title": "i need your opinion guys"}, {"image": "https://i.redd.it/v74cny84d4rc1.png", "subreddit": "blursedimages", "title": "Blursed Ash"}, {"image": "https://i.redd.it/8ztjhdhap3rc1.png", "subreddit": "tattoos", "title": "Tat done by Gabrielle Poisson at Lucky's Tattoo in Cambridge, MA"}, {"image": "https://i.redd.it/9bc0xcsmd5rc1.png", "subreddit": "astrophotography", "title": "Orion's nebula third try "}, {"image": "https://i.redd.it/l5e5j65f82rc1.png", "subreddit": "pics", "title": "Einstein and Oppenheimer, 1930s"}, {"image": "https://i.redd.it/gm2qbx9br3rc1.png", "subreddit": "cats", "title": "$500 gaming console? No, $500 cat chair apparently. "}]